rpy/__init__.py
rpy/__main__.py
rpy/cli/__init__.py
rpy/cli/dispatch.py
rpy/cli/utils.py
rpy/cli/commands/__init__.py
rpy/cli/commands/create_password.py
rpy/cli/commands/pass.py
rpy/cli/commands/refactor.py
rpy/cli/commands/test.py
rpy/dataframe/__init__.py
rpy/dataframe/csv.py
rpy/dataframe/excel.py
rpy/functions/__init__.py
rpy/functions/api.py
rpy/functions/asyncio.py
rpy/functions/datastructures.py
rpy/functions/debug.py
rpy/functions/decorators.py
rpy/functions/dispatch.py
rpy/functions/encoding.py
rpy/functions/functional.py
rpy/functions/importutils.py
rpy/functions/pbcopy.py
rpy/functions/process.py
rpy/functions/require.py
rpy/functions/six.py
rpy/password/__init__.py
rpy/password/keychain.py
rpy/tests/__init__.py
rpy/tests/functions.py
rpy/tests/keychain.py
python_rpy-1.0.17.dist-info/LICENSE
python_rpy-1.0.17.dist-info/METADATA
python_rpy-1.0.17.dist-info/WHEEL
python_rpy-1.0.17.dist-info/top_level.txt
python_rpy-1.0.17.dist-info/RECORD
