Metadata-Version: 2.1
Name: python-rpy
Version: 1.0.17
Summary: A Python library with various functional tools.
Home-page: UNKNOWN
Author: Riccardo Di Virgilio
Author-email: riccardodivirgilio@gmail.com
License: UNKNOWN
Keywords: password
Platform: UNKNOWN
Requires-Python: >=3.5
